rtl/reram_controller.v
`timescale 1ns / 1ps

//==============================================================================
// ReRAM Accelerator Controller - FIXED FSM
// Function: Controls the dataflow for ReRAM-based inference
//==============================================================================

module reram_controller #(
    parameter INPUT_WIDTH = 8,
    parameter OUTPUT_WIDTH = 12,
    parameter INPUT_SIZE = 784,
    parameter OUTPUT_SIZE = 256
)(
    input  wire                     clk,
    input  wire                     rst_n,
    
    // Control signals
    input  wire                     start,
    output reg                      done,
    output reg                      busy,
    
    // Input interface
    input  wire [INPUT_WIDTH-1:0]   input_data,
    input  wire                     input_valid,
    output reg                      input_ready,
    
    // DAC interface
    output reg  [9:0]               dac_out,
    output reg                      dac_valid,
    
    // Crossbar interface
    output reg                      xbar_enable,
    output reg  [9:0]               xbar_addr,
    input  wire [OUTPUT_WIDTH-1:0]  xbar_data,
    input  wire                     xbar_valid,
    
    // Output interface
    output reg  [OUTPUT_WIDTH-1:0]  output_data,
    output reg  [7:0]               output_addr,
    output reg                      output_valid
);

    //--------------------------------------------------------------------------
    // FSM States
    //--------------------------------------------------------------------------
    localparam IDLE         = 3'b000;
    localparam LOAD_INPUT   = 3'b001;
    localparam COMPUTE_WAIT = 3'b010;
    localparam COMPUTE_DONE = 3'b011;
    localparam OUTPUT_WRITE = 3'b100;
    localparam DONE_STATE   = 3'b101;
    
    reg [2:0] state, next_state;
    
    //--------------------------------------------------------------------------
    // Internal Registers
    //--------------------------------------------------------------------------
    reg [9:0]  input_counter;
    reg [8:0]  output_counter;  // Changed to 9 bits to hold 256
    reg [15:0] wait_counter;
    
    // Input buffer
    reg [INPUT_WIDTH-1:0] input_buffer [0:INPUT_SIZE-1];
    
    // Output buffer
    reg [OUTPUT_WIDTH-1:0] output_buffer [0:OUTPUT_SIZE-1];
    
    // Computation state
    reg computing;
    reg [9:0] current_neuron;
    
    //--------------------------------------------------------------------------
    // State Machine - Sequential
    //--------------------------------------------------------------------------
    always @(posedge clk or negedge rst_n) begin
        if (!rst_n) begin
            state <= IDLE;
        end else begin
            state <= next_state;
        end
    end
    
    //--------------------------------------------------------------------------
    // State Machine - Combinational (Next State Logic)
    //--------------------------------------------------------------------------
    always @(*) begin
        next_state = state;
        
        case (state)
            IDLE: begin
                if (start) begin
                    next_state = LOAD_INPUT;
                end
            end
            
            LOAD_INPUT: begin
                if (input_counter == INPUT_SIZE && input_valid) begin
                    next_state = COMPUTE_WAIT;
                end
            end
            
            COMPUTE_WAIT: begin
                if (xbar_valid) begin
                    next_state = COMPUTE_DONE;
                end
            end
            
            COMPUTE_DONE: begin
                next_state = OUTPUT_WRITE;
            end
            
            OUTPUT_WRITE: begin
                if (current_neuron == OUTPUT_SIZE - 1) begin
                    next_state = DONE_STATE;
                end else begin
                    next_state = COMPUTE_WAIT;
                end
            end
            
            DONE_STATE: begin
                next_state = IDLE;
            end
            
            default: begin
                next_state = IDLE;
            end
        endcase
    end
    
    //--------------------------------------------------------------------------
    // State Machine - Output Logic
    //--------------------------------------------------------------------------
    always @(posedge clk or negedge rst_n) begin
        if (!rst_n) begin
            done            <= 1'b0;
            busy            <= 1'b0;
            input_ready     <= 1'b0;
            dac_out         <= 10'b0;
            dac_valid       <= 1'b0;
            xbar_enable     <= 1'b0;
            xbar_addr       <= 10'b0;
            output_data     <= {OUTPUT_WIDTH{1'b0}};
            output_addr     <= 8'b0;
            output_valid    <= 1'b0;
            input_counter   <= 10'b0;
            output_counter  <= 9'b0;
            wait_counter    <= 16'b0;
            computing       <= 1'b0;
            current_neuron  <= 10'b0;
        end else begin
            // Default outputs
            input_ready  <= 1'b0;
            dac_valid    <= 1'b0;
            xbar_enable  <= 1'b0;
            output_valid <= 1'b0;
            done         <= 1'b0;
            
            case (state)
                IDLE: begin
                    busy           <= 1'b0;
                    input_counter  <= 10'b0;
                    output_counter <= 9'b0;
                    wait_counter   <= 16'b0;
                    computing      <= 1'b0;
                    current_neuron <= 10'b0;
                    
                    if (start) begin
                        busy <= 1'b1;
                    end
                end
                
                LOAD_INPUT: begin
                    busy        <= 1'b1;
                    input_ready <= 1'b1;
                    
                    if (input_valid) begin
                        input_buffer[input_counter] <= input_data;
                        
                        if (input_counter < INPUT_SIZE) begin
                            input_counter <= input_counter + 1'b1;
                        end
                    end
                end
                
                COMPUTE_WAIT: begin
                    busy        <= 1'b1;
                    xbar_enable <= 1'b1;
                    xbar_addr   <= current_neuron;
                    
                    // Send DAC output (use first input for now - simplified)
                    dac_out   <= {input_buffer[0], 2'b00};
                    dac_valid <= 1'b1;
                end
                
                COMPUTE_DONE: begin
                    busy <= 1'b1;
                    // Store result
                    output_buffer[current_neuron] <= xbar_data;
                end
                
                OUTPUT_WRITE: begin
                    busy         <= 1'b1;
                    output_data  <= output_buffer[current_neuron];
                    output_addr  <= current_neuron[7:0];
                    output_valid <= 1'b1;
                    
                    if (current_neuron < OUTPUT_SIZE - 1) begin
                        current_neuron <= current_neuron + 1'b1;
                    end
                end
                
                DONE_STATE: begin
                    done            <= 1'b1;
                    busy            <= 1'b0;
                    input_counter   <= 10'b0;
                    output_counter  <= 9'b0;
                    current_neuron  <= 10'b0;
                end
                
                default: begin
                    busy <= 1'b0;
                end
            endcase
        end
    end

endmodule

testbench/tb_reram_controller.v
`timescale 1ns / 1ps

//==============================================================================
// Testbench for ReRAM Controller - FIXED VERSION
// Tests: Load input → DAC → Crossbar (mock) → ADC → Output
//==============================================================================

module tb_reram_controller;

    //--------------------------------------------------------------------------
    // Parameters
    //--------------------------------------------------------------------------
    parameter CLK_PERIOD = 10;  // 10ns = 100MHz
    parameter INPUT_SIZE = 784;
    parameter OUTPUT_SIZE = 256;
    
    //--------------------------------------------------------------------------
    // DUT Signals
    //--------------------------------------------------------------------------
    reg                 clk;
    reg                 rst_n;
    reg                 start;
    wire                done;
    wire                busy;
    
    reg  [7:0]          input_data;
    reg                 input_valid;
    wire                input_ready;
    
    wire [9:0]          dac_out;
    wire                dac_valid;
    
    wire                xbar_enable;
    wire [9:0]          xbar_addr;
    reg  [11:0]         xbar_data;
    reg                 xbar_valid;
    
    wire [11:0]         output_data;
    wire [7:0]          output_addr;
    wire                output_valid;
    
    //--------------------------------------------------------------------------
    // Test Variables
    //--------------------------------------------------------------------------
    integer i;
    integer input_count;
    integer output_count;
    integer errors;
    
    // Test input data (simplified MNIST-like pattern)
    reg [7:0] test_input [0:INPUT_SIZE-1];
    reg [11:0] expected_output [0:OUTPUT_SIZE-1];
    
    //--------------------------------------------------------------------------
    // Clock Generation
    //--------------------------------------------------------------------------
    initial begin
        clk = 0;
        forever #(CLK_PERIOD/2) clk = ~clk;
    end
    
    //--------------------------------------------------------------------------
    // DUT Instantiation
    //--------------------------------------------------------------------------
    reram_controller #(
        .INPUT_WIDTH(8),
        .OUTPUT_WIDTH(12),
        .INPUT_SIZE(INPUT_SIZE),
        .OUTPUT_SIZE(OUTPUT_SIZE)
    ) dut (
        .clk(clk),
        .rst_n(rst_n),
        .start(start),
        .done(done),
        .busy(busy),
        .input_data(input_data),
        .input_valid(input_valid),
        .input_ready(input_ready),
        .dac_out(dac_out),
        .dac_valid(dac_valid),
        .xbar_enable(xbar_enable),
        .xbar_addr(xbar_addr),
        .xbar_data(xbar_data),
        .xbar_valid(xbar_valid),
        .output_data(output_data),
        .output_addr(output_addr),
        .output_valid(output_valid)
    );
    
    //--------------------------------------------------------------------------
    // Mock Crossbar Response (Simulates ReRAM computation)
    //--------------------------------------------------------------------------
    reg [3:0] xbar_delay_counter;
    
    always @(posedge clk or negedge rst_n) begin
        if (!rst_n) begin
            xbar_valid <= 1'b0;
            xbar_data <= 12'b0;
            xbar_delay_counter <= 4'b0;
        end else begin
            xbar_valid <= 1'b0;  // Default
            
            if (xbar_enable) begin
                if (xbar_delay_counter < 4'd10) begin
                    xbar_delay_counter <= xbar_delay_counter + 1'b1;
                end else begin
                    // Mock computation: output = input * weight_factor
                    xbar_data <= (dac_out * 4) % 4096;
                    xbar_valid <= 1'b1;
                    xbar_delay_counter <= 4'b0;
                end
            end else begin
                xbar_delay_counter <= 4'b0;
            end
        end
    end
    
    //--------------------------------------------------------------------------
    // Initialize Test Data
    //--------------------------------------------------------------------------
    initial begin
        // Generate test pattern (simulating MNIST digit "1")
        for (i = 0; i < INPUT_SIZE; i = i + 1) begin
            if (i >= 300 && i < 500) begin
                test_input[i] = 8'd255;  // Bright pixels in center
            end else begin
                test_input[i] = 8'd0;    // Dark pixels elsewhere
            end
        end
        
        // Expected outputs (mock - for verification)
        for (i = 0; i < OUTPUT_SIZE; i = i + 1) begin
            expected_output[i] = 12'd2048;  // Placeholder
        end
    end
    
    //--------------------------------------------------------------------------
    // Output Monitor (runs in parallel)
    //--------------------------------------------------------------------------
    always @(posedge clk) begin
        if (output_valid) begin
            output_count = output_count + 1;
            if (output_count % 50 == 0) begin
                $display("  Output %0d: addr=%0d, data=%0d", 
                       output_count, output_addr, output_data);
            end
        end
    end
    
    //--------------------------------------------------------------------------
    // Test Stimulus
    //--------------------------------------------------------------------------
    initial begin
        // Initialize signals
        rst_n = 0;
        start = 0;
        input_data = 8'b0;
        input_valid = 0;
        input_count = 0;
        output_count = 0;
        errors = 0;
        
        // Dump waveforms
        $dumpfile("sim/reram_controller.vcd");
        $dumpvars(0, tb_reram_controller);
        
        // Reset
        #(CLK_PERIOD * 5);
        rst_n = 1;
        #(CLK_PERIOD * 2);
        
        $display("========================================");
        $display("ReRAM Controller Testbench");
        $display("========================================");
        $display("Time: %0t - Starting test...", $time);
        
        // Start inference
        start = 1;
        #(CLK_PERIOD);
        start = 0;
        
        // Wait for controller to be ready
        while (busy == 0) begin
            @(posedge clk);
        end
        $display("Time: %0t - Controller active", $time);
        
        // Load input data
        $display("Time: %0t - Loading %0d inputs...", $time, INPUT_SIZE);
        for (i = 0; i < INPUT_SIZE; i = i + 1) begin
            // Wait for ready signal
            while (input_ready == 0) begin
                @(posedge clk);
            end
            
            @(posedge clk);
            input_data = test_input[i];
            input_valid = 1;
            @(posedge clk);
            input_valid = 0;
            
            if (i % 100 == 0) begin
                $display("  Loaded %0d/%0d inputs", i, INPUT_SIZE);
            end
        end
        
        $display("Time: %0t - All inputs loaded", $time);
        
        // Wait for completion
        while (done == 0) begin
            @(posedge clk);
        end
        
        $display("Time: %0t - Inference complete!", $time);
        $display("  Total outputs: %0d", output_count);
        
        // Check results
        #(CLK_PERIOD * 10);
        
        if (output_count == OUTPUT_SIZE) begin
            $display("");
            $display("+ TEST PASSED: All %0d outputs generated", OUTPUT_SIZE);
        end else begin
            $display("");
            $display("X TEST FAILED: Expected %0d outputs, got %0d", 
                   OUTPUT_SIZE, output_count);
            errors = errors + 1;
        end
        
        $display("========================================");
        $display("Test Summary:");
        $display("  Inputs loaded:  %0d", INPUT_SIZE);
        $display("  Outputs generated: %0d", output_count);
        $display("  Errors: %0d", errors);
        $display("========================================");
        
        if (errors == 0) begin
            $display("+ ALL TESTS PASSED");
        end else begin
            $display("X TESTS FAILED (%0d errors)", errors);
        end
        
        $finish;
    end
    
    //--------------------------------------------------------------------------
    // Timeout Watchdog
    //--------------------------------------------------------------------------
    initial begin
        #(CLK_PERIOD * 1000000);  // 10ms timeout
        $display("");
        $display("X ERROR: Test timeout!");
        $finish;
    end

endmodule

sim/reram_controller.vcd
$date
	Thu Dec 04 14:12:24 2025
$end
$version
	Icarus Verilog
$end
$timescale
	1ps
$end
$scope module tb_reram_controller $end
$var wire 1 ! xbar_enable $end
$var wire 10 " xbar_addr [9:0] $end
$var wire 1 # output_valid $end
$var wire 12 $ output_data [11:0] $end
$var wire 8 % output_addr [7:0] $end
$var wire 1 & input_ready $end
$var wire 1 ' done $end
$var wire 1 ( dac_valid $end
$var wire 10 ) dac_out [9:0] $end
$var wire 1 * busy $end
$var reg 1 + clk $end
$var reg 8 , input_data [7:0] $end
$var reg 1 - input_valid $end
$var reg 1 . rst_n $end
$var reg 1 / start $end
$var reg 12 0 xbar_data [11:0] $end
$var reg 4 1 xbar_delay_counter [3:0] $end
$var reg 1 2 xbar_valid $end
$var integer 32 3 errors [31:0] $end
$var integer 32 4 i [31:0] $end
$var integer 32 5 input_count [31:0] $end
$var integer 32 6 output_count [31:0] $end
$scope module dut $end
$var wire 1 + clk $end
$var wire 8 7 input_data [7:0] $end
$var wire 1 - input_valid $end
$var wire 1 . rst_n $end
$var wire 1 / start $end
$var wire 12 8 xbar_data [11:0] $end
$var wire 1 2 xbar_valid $end
$var reg 1 * busy $end
$var reg 1 9 computing $end
$var reg 10 : current_neuron [9:0] $end
$var reg 10 ; dac_out [9:0] $end
$var reg 1 ( dac_valid $end
$var reg 1 ' done $end
$var reg 10 < input_counter [9:0] $end
$var reg 1 & input_ready $end
$var reg 3 = next_state [2:0] $end
$var reg 8 > output_addr [7:0] $end
$var reg 9 ? output_counter [8:0] $end
$var reg 12 @ output_data [11:0] $end
$var reg 1 # output_valid $end
$var reg 3 A state [2:0] $end
$var reg 16 B wait_counter [15:0] $end
$var reg 10 C xbar_addr [9:0] $end
$var reg 1 ! xbar_enable $end
$upscope $end
$upscope $end
$enddefinitions $end
#0
$dumpvars
b0 C
b0 B
b0 A
b0 @
b0 ?
b0 >
b0 =
b0 <
b0 ;
b0 :
09
b0 8
b0 7
b0 6
b0 5
b100000000 4
b0 3
02
b0 1
b0 0
0/
0.
0-
b0 ,
0+
0*
b0 )
0(
0'
0&
b0 %
b0 $
0#
b0 "
0!
$end
#5000
1+
#10000
0+
#15000
1+
#20000
0+
#25000
1+
#30000
0+
#35000
1+
#40000
0+
#45000
1+
#50000
0+
1.
#55000
1+
#60000
0+
#65000
1+
#70000
b1 =
0+
1/
#75000
b1 A
1*
1+
#80000
0+
b0 4
0/
#85000
1&
1+
#90000
0+
#95000
1&
1+
#100000
0+
#105000
b1 <
1&
1-
1+
#110000
0+
#115000
1&
b1 4
0-
1+
#120000
0+
#125000
b10 <
1&
1-
1+
#130000
0+
#135000
1&
b10 4
0-
1+
#140000
0+
#145000
b11 <
1&
1-
1+
#150000
0+
#155000
1&
b11 4
0-
1+
#160000
0+
#165000
b100 <
1&
1-
1+
#170000
0+
#175000
1&
b100 4
0-
1+
#180000
0+
#185000
b101 <
1&
1-
1+
#190000
0+
#195000
1&
b101 4
0-
1+
#200000
0+
#205000
b110 <
1&
1-
1+
#210000
0+
#215000
1&
b110 4
0-
1+
#220000
0+
#225000
b111 <
1&
1-
1+
#230000
0+
#235000
1&
b111 4
0-
1+
#240000
0+
#245000
b1000 <
1&
1-
1+
#250000
0+
#255000
1&
b1000 4
0-
1+
#260000
0+
#265000
b1001 <
1&
1-
1+
#270000
0+
#275000
1&
b1001 4
0-
1+
#280000
0+
#285000
b1010 <
1&
1-
1+
#290000
0+
#295000
1&
b1010 4
0-
1+
#300000
0+
#305000
b1011 <
1&
1-
1+
#310000
0+
#315000
1&
b1011 4
0-
1+
#320000
0+
#325000
b1100 <
1&
1-
1+
#330000
0+
#335000
1&
b1100 4
0-
1+
#340000
0+
#345000
b1101 <
1&
1-
1+
#350000
0+
#355000
1&
b1101 4
0-
1+
#360000
0+
#365000
b1110 <
1&
1-
1+
#370000
0+
#375000
1&
b1110 4
0-
1+
#380000
0+
#385000
b1111 <
1&
1-
1+
#390000
0+
#395000
1&
b1111 4
0-
1+
#400000
0+
#405000
b10000 <
1&
1-
1+
#410000
0+
#415000
1&
b10000 4
0-
1+
#420000
0+
#425000
b10001 <
1&
1-
1+
#430000
0+
#435000
1&
b10001 4
0-
1+
#440000
0+
#445000
b10010 <
1&
1-
1+
#450000
0+
#455000
1&
b10010 4
0-
1+
#460000
0+
#465000
b10011 <
1&
1-
1+
#470000
0+
#475000
1&
b10011 4
0-
1+
#480000
0+
#485000
b10100 <
1&
1-
1+
#490000
0+
#495000
1&
b10100 4
0-
1+
#500000
0+
#505000
b10101 <
1&
1-
1+
#510000
0+
#515000
1&
b10101 4
0-
1+
#520000
0+
#525000
b10110 <
1&
1-
1+
#530000
0+
#535000
1&
b10110 4
0-
1+
#540000
0+
#545000
b10111 <
1&
1-
1+
#550000
0+
#555000
1&
b10111 4
0-
1+
#560000
0+
#565000
b11000 <
1&
1-
1+
#570000
0+
#575000
1&
b11000 4
0-
1+
#580000
0+
#585000
b11001 <
1&
1-
1+
#590000
0+
#595000
1&
b11001 4
0-
1+
#600000
0+
#605000
b11010 <
1&
1-
1+
#610000
0+
#615000
1&
b11010 4
0-
1+
#620000
0+
#625000
b11011 <
1&
1-
1+
#630000
0+
#635000
1&
b11011 4
0-
1+
#640000
0+
#645000
b11100 <
1&
1-
1+
#650000
0+
#655000
1&
b11100 4
0-
1+
#660000
0+
#665000
b11101 <
1&
1-
1+
#670000
0+
#675000
1&
b11101 4
0-
1+
#680000
0+
#685000
b11110 <
1&
1-
1+
#690000
0+
#695000
1&
b11110 4
0-
1+
#700000
0+
#705000
b11111 <
1&
1-
1+
#710000
0+
#715000
1&
b11111 4
0-
1+
#720000
0+
#725000
b100000 <
1&
1-
1+
#730000
0+
#735000
1&
b100000 4
0-
1+
#740000
0+
#745000
b100001 <
1&
1-
1+
#750000
0+
#755000
1&
b100001 4
0-
1+
#760000
0+
#765000
b100010 <
1&
1-
1+
#770000
0+
#775000
1&
b100010 4
0-
1+
#780000
0+
#785000
b100011 <
1&
1-
1+
#790000
0+
#795000
1&
b100011 4
0-
1+
#800000
0+
#805000
b100100 <
1&
1-
1+
#810000
0+
#815000
1&
b100100 4
0-
1+
#820000
0+
#825000
b100101 <
1&
1-
1+
#830000
0+
#835000
1&
b100101 4
0-
1+
#840000
0+
#845000
b100110 <
1&
1-
1+
#850000
0+
#855000
1&
b100110 4
0-
1+
#860000
0+
#865000
b100111 <
1&
1-
1+
#870000
0+
#875000
1&
b100111 4
0-
1+
#880000
0+
#885000
b101000 <
1&
1-
1+
#890000
0+
#895000
1&
b101000 4
0-
1+
#900000
0+
#905000
b101001 <
1&
1-
1+
#910000
0+
#915000
1&
b101001 4
0-
1+
#920000
0+
#925000
b101010 <
1&
1-
1+
#930000
0+
#935000
1&
b101010 4
0-
1+
#940000
0+
#945000
b101011 <
1&
1-
1+
#950000
0+
#955000
1&
b101011 4
0-
1+
#960000
0+
#965000
b101100 <
1&
1-
1+
#970000
0+
#975000
1&
b101100 4
0-
1+
#980000
0+
#985000
b101101 <
1&
1-
1+
#990000
0+
#995000
1&
b101101 4
0-
1+
#1000000
0+
#1005000
b101110 <
1&
1-
1+
#1010000
0+
#1015000
1&
b101110 4
0-
1+
#1020000
0+
#1025000
b101111 <
1&
1-
1+
#1030000
0+
#1035000
1&
b101111 4
0-
1+
#1040000
0+
#1045000
b110000 <
1&
1-
1+
#1050000
0+
#1055000
1&
b110000 4
0-
1+
#1060000
0+
#1065000
b110001 <
1&
1-
1+
#1070000
0+
#1075000
1&
b110001 4
0-
1+
#1080000
0+
#1085000
b110010 <
1&
1-
1+
#1090000
0+
#1095000
1&
b110010 4
0-
1+
#1100000
0+
#1105000
b110011 <
1&
1-
1+
#1110000
0+
#1115000
1&
b110011 4
0-
1+
#1120000
0+
#1125000
b110100 <
1&
1-
1+
#1130000
0+
#1135000
1&
b110100 4
0-
1+
#1140000
0+
#1145000
b110101 <
1&
1-
1+
#1150000
0+
#1155000
1&
b110101 4
0-
1+
#1160000
0+
#1165000
b110110 <
1&
1-
1+
#1170000
0+
#1175000
1&
b110110 4
0-
1+
#1180000
0+
#1185000
b110111 <
1&
1-
1+
#1190000
0+
#1195000
1&
b110111 4
0-
1+
#1200000
0+
#1205000
b111000 <
1&
1-
1+
#1210000
0+
#1215000
1&
b111000 4
0-
1+
#1220000
0+
#1225000
b111001 <
1&
1-
1+
#1230000
0+
#1235000
1&
b111001 4
0-
1+
#1240000
0+
#1245000
b111010 <
1&
1-
1+
#1250000
0+
#1255000
1&
b111010 4
0-
1+
#1260000
0+
#1265000
b111011 <
1&
1-
1+
#1270000
0+
#1275000
1&
b111011 4
0-
1+
#1280000
0+
#1285000
b111100 <
1&
1-
1+
#1290000
0+
#1295000
1&
b111100 4
0-
1+
#1300000
0+
#1305000
b111101 <
1&
1-
1+
#1310000
0+
#1315000
1&
b111101 4
0-
1+
#1320000
0+
#1325000
b111110 <
1&
1-
1+
#1330000
0+
#1335000
1&
b111110 4
0-
1+
#1340000
0+
#1345000
b111111 <
1&
1-
1+
#1350000
0+
#1355000
1&
b111111 4
0-
1+
#1360000
0+
#1365000
b1000000 <
1&
1-
1+
#1370000
0+
#1375000
1&
b1000000 4
0-
1+
#1380000
0+
#1385000
b1000001 <
1&
1-
1+
#1390000
0+
#1395000
1&
b1000001 4
0-
1+
#1400000
0+
#1405000
b1000010 <
1&
1-
1+
#1410000
0+
#1415000
1&
b1000010 4
0-
1+
#1420000
0+
#1425000
b1000011 <
1&
1-
1+
#1430000
0+
#1435000
1&
b1000011 4
0-
1+
#1440000
0+
#1445000
b1000100 <
1&
1-
1+
#1450000
0+
#1455000
1&
b1000100 4
0-
1+
#1460000
0+
#1465000
b1000101 <
1&
1-
1+
#1470000
0+
#1475000
1&
b1000101 4
0-
1+
#1480000
0+
#1485000
b1000110 <
1&
1-
1+
#1490000
0+
#1495000
1&
b1000110 4
0-
1+
#1500000
0+
#1505000
b1000111 <
1&
1-
1+
#1510000
0+
#1515000
1&
b1000111 4
0-
1+
#1520000
0+
#1525000
b1001000 <
1&
1-
1+
#1530000
0+
#1535000
1&
b1001000 4
0-
1+
#1540000
0+
#1545000
b1001001 <
1&
1-
1+
#1550000
0+
#1555000
1&
b1001001 4
0-
1+
#1560000
0+
#1565000
b1001010 <
1&
1-
1+
#1570000
0+
#1575000
1&
b1001010 4
0-
1+
#1580000
0+
#1585000
b1001011 <
1&
1-
1+
#1590000
0+
#1595000
1&
b1001011 4
0-
1+
#1600000
0+
#1605000
b1001100 <
1&
1-
1+
#1610000
0+
#1615000
1&
b1001100 4
0-
1+
#1620000
0+
#1625000
b1001101 <
1&
1-
1+
#1630000
0+
#1635000
1&
b1001101 4
0-
1+
#1640000
0+
#1645000
b1001110 <
1&
1-
1+
#1650000
0+
#1655000
1&
b1001110 4
0-
1+
#1660000
0+
#1665000
b1001111 <
1&
1-
1+
#1670000
0+
#1675000
1&
b1001111 4
0-
1+
#1680000
0+
#1685000
b1010000 <
1&
1-
1+
#1690000
0+
#1695000
1&
b1010000 4
0-
1+
#1700000
0+
#1705000
b1010001 <
1&
1-
1+
#1710000
0+
#1715000
1&
b1010001 4
0-
1+
#1720000
0+
#1725000
b1010010 <
1&
1-
1+
#1730000
0+
#1735000
1&
b1010010 4
0-
1+
#1740000
0+
#1745000
b1010011 <
1&
1-
1+
#1750000
0+
#1755000
1&
b1010011 4
0-
1+
#1760000
0+
#1765000
b1010100 <
1&
1-
1+
#1770000
0+
#1775000
1&
b1010100 4
0-
1+
#1780000
0+
#1785000
b1010101 <
1&
1-
1+
#1790000
0+
#1795000
1&
b1010101 4
0-
1+
#1800000
0+
#1805000
b1010110 <
1&
1-
1+
#1810000
0+
#1815000
1&
b1010110 4
0-
1+
#1820000
0+
#1825000
b1010111 <
1&
1-
1+
#1830000
0+
#1835000
1&
b1010111 4
0-
1+
#1840000
0+
#1845000
b1011000 <
1&
1-
1+
#1850000
0+
#1855000
1&
b1011000 4
0-
1+
#1860000
0+
#1865000
b1011001 <
1&
1-
1+
#1870000
0+
#1875000
1&
b1011001 4
0-
1+
#1880000
0+
#1885000
b1011010 <
1&
1-
1+
#1890000
0+
#1895000
1&
b1011010 4
0-
1+
#1900000
0+
#1905000
b1011011 <
1&
1-
1+
#1910000
0+
#1915000
1&
b1011011 4
0-
1+
#1920000
0+
#1925000
b1011100 <
1&
1-
1+
#1930000
0+
#1935000
1&
b1011100 4
0-
1+
#1940000
0+
#1945000
b1011101 <
1&
1-
1+
#1950000
0+
#1955000
1&
b1011101 4
0-
1+
#1960000
0+
#1965000
b1011110 <
1&
1-
1+
#1970000
0+
#1975000
1&
b1011110 4
0-
1+
#1980000
0+
#1985000
b1011111 <
1&
1-
1+
#1990000
0+
#1995000
1&
b1011111 4
0-
1+
#2000000
0+
#2005000
b1100000 <
1&
1-
1+
#2010000
0+
#2015000
1&
b1100000 4
0-
1+
#2020000
0+
#2025000
b1100001 <
1&
1-
1+
#2030000
0+
#2035000
1&
b1100001 4
0-
1+
#2040000
0+
#2045000
b1100010 <
1&
1-
1+
#2050000
0+
#2055000
1&
b1100010 4
0-
1+
#2060000
0+
#2065000
b1100011 <
1&
1-
1+
#2070000
0+
#2075000
1&
b1100011 4
0-
1+
#2080000
0+
#2085000
b1100100 <
1&
1-
1+
#2090000
0+
#2095000
1&
b1100100 4
0-
1+
#2100000
0+
#2105000
b1100101 <
1&
1-
1+
#2110000
0+
#2115000
1&
b1100101 4
0-
1+
#2120000
0+
#2125000
b1100110 <
1&
1-
1+
#2130000
0+
#2135000
1&
b1100110 4
0-
1+
#2140000
0+
#2145000
b1100111 <
1&
1-
1+
#2150000
0+
#2155000
1&
b1100111 4
0-
1+
#2160000
0+
#2165000
b1101000 <
1&
1-
1+
#2170000
0+
#2175000
1&
b1101000 4
0-
1+
#2180000
0+
#2185000
b1101001 <
1&
1-
1+
#2190000
0+
#2195000
1&
b1101001 4
0-
1+
#2200000
0+
#2205000
b1101010 <
1&
1-
1+
#2210000
0+
#2215000
1&
b1101010 4
0-
1+
#2220000
0+
#2225000
b1101011 <
1&
1-
1+
#2230000
0+
#2235000
1&
b1101011 4
0-
1+
#2240000
0+
#2245000
b1101100 <
1&
1-
1+
#2250000
0+
#2255000
1&
b1101100 4
0-
1+
#2260000
0+
#2265000
b1101101 <
1&
1-
1+
#2270000
0+
#2275000
1&
b1101101 4
0-
1+
#2280000
0+
#2285000
b1101110 <
1&
1-
1+
#2290000
0+
#2295000
1&
b1101110 4
0-
1+
#2300000
0+
#2305000
b1101111 <
1&
1-
1+
#2310000
0+
#2315000
1&
b1101111 4
0-
1+
#2320000
0+
#2325000
b1110000 <
1&
1-
1+
#2330000
0+
#2335000
1&
b1110000 4
0-
1+
#2340000
0+
#2345000
b1110001 <
1&
1-
1+
#2350000
0+
#2355000
1&
b1110001 4
0-
1+
#2360000
0+
#2365000
b1110010 <
1&
1-
1+
#2370000
0+
#2375000
1&
b1110010 4
0-
1+
#2380000
0+
#2385000
b1110011 <
1&
1-
1+
#2390000
0+
#2395000
1&
b1110011 4
0-
1+
#2400000
0+
#2405000
b1110100 <
1&
1-
1+
#2410000
0+
#2415000
1&
b1110100 4
0-
1+
#2420000
0+
#2425000
b1110101 <
1&
1-
1+
#2430000
0+
#2435000
1&
b1110101 4
0-
1+
#2440000
0+
#2445000
b1110110 <
1&
1-
1+
#2450000
0+
#2455000
1&
b1110110 4
0-
1+
#2460000
0+
#2465000
b1110111 <
1&
1-
1+
#2470000
0+
#2475000
1&
b1110111 4
0-
1+
#2480000
0+
#2485000
b1111000 <
1&
1-
1+
#2490000
0+
#2495000
1&
b1111000 4
0-
1+
#2500000
0+
#2505000
b1111001 <
1&
1-
1+
#2510000
0+
#2515000
1&
b1111001 4
0-
1+
#2520000
0+
#2525000
b1111010 <
1&
1-
1+
#2530000
0+
#2535000
1&
b1111010 4
0-
1+
#2540000
0+
#2545000
b1111011 <
1&
1-
1+
#2550000
0+
#2555000
1&
b1111011 4
0-
1+
#2560000
0+
#2565000
b1111100 <
1&
1-
1+
#2570000
0+
#2575000
1&
b1111100 4
0-
1+
#2580000
0+
#2585000
b1111101 <
1&
1-
1+
#2590000
0+
#2595000
1&
b1111101 4
0-
1+
#2600000
0+
#2605000
b1111110 <
1&
1-
1+
#2610000
0+
#2615000
1&
b1111110 4
0-
1+
#2620000
0+
#2625000
b1111111 <
1&
1-
1+
#2630000
0+
#2635000
1&
b1111111 4
0-
1+
#2640000
0+
#2645000
b10000000 <
1&
1-
1+
#2650000
0+
#2655000
1&
b10000000 4
0-
1+
#2660000
0+
#2665000
b10000001 <
1&
1-
1+
#2670000
0+
#2675000
1&
b10000001 4
0-
1+
#2680000
0+
#2685000
b10000010 <
1&
1-
1+
#2690000
0+
#2695000
1&
b10000010 4
0-
1+
#2700000
0+
#2705000
b10000011 <
1&
1-
1+
#2710000
0+
#2715000
1&
b10000011 4
0-
1+
#2720000
0+
#2725000
b10000100 <
1&
1-
1+
#2730000
0+
#2735000
1&
b10000100 4
0-
1+
#2740000
0+
#2745000
b10000101 <
1&
1-
1+
#2750000
0+
#2755000
1&
b10000101 4
0-
1+
#2760000
0+
#2765000
b10000110 <
1&
1-
1+
#2770000
0+
#2775000
1&
b10000110 4
0-
1+
#2780000
0+
#2785000
b10000111 <
1&
1-
1+
#2790000
0+
#2795000
1&
b10000111 4
0-
1+
#2800000
0+
#2805000
b10001000 <
1&
1-
1+
#2810000
0+
#2815000
1&
b10001000 4
0-
1+
#2820000
0+
#2825000
b10001001 <
1&
1-
1+
#2830000
0+
#2835000
1&
b10001001 4
0-
1+
#2840000
0+
#2845000
b10001010 <
1&
1-
1+
#2850000
0+
#2855000
1&
b10001010 4
0-
1+
#2860000
0+
#2865000
b10001011 <
1&
1-
1+
#2870000
0+
#2875000
1&
b10001011 4
0-
1+
#2880000
0+
#2885000
b10001100 <
1&
1-
1+
#2890000
0+
#2895000
1&
b10001100 4
0-
1+
#2900000
0+
#2905000
b10001101 <
1&
1-
1+
#2910000
0+
#2915000
1&
b10001101 4
0-
1+
#2920000
0+
#2925000
b10001110 <
1&
1-
1+
#2930000
0+
#2935000
1&
b10001110 4
0-
1+
#2940000
0+
#2945000
b10001111 <
1&
1-
1+
#2950000
0+
#2955000
1&
b10001111 4
0-
1+
#2960000
0+
#2965000
b10010000 <
1&
1-
1+
#2970000
0+
#2975000
1&
b10010000 4
0-
1+
#2980000
0+
#2985000
b10010001 <
1&
1-
1+
#2990000
0+
